tensorcomlib/__init__.py
tensorcomlib/__version__.py
tensorcomlib/tensor.py
tensorcomlib/base/__init__.py
tensorcomlib/base/base.py
tensorcomlib/decomposition/__init__.py
tensorcomlib/decomposition/cp.py
tensorcomlib/decomposition/tucker.py
tensorcomlib/matrix/SVD.py
tensorcomlib/matrix/__init__.py
tensorcomlib/random/__init__.py
tensorcomlib/random/random.py
tensorcomlib/tools/__init__.py
tensorcomlib/tools/tools.py
tensorcomlib-1.7.0.dist-info/DESCRIPTION.rst
tensorcomlib-1.7.0.dist-info/METADATA
tensorcomlib-1.7.0.dist-info/RECORD
tensorcomlib-1.7.0.dist-info/WHEEL
tensorcomlib-1.7.0.dist-info/metadata.json
tensorcomlib-1.7.0.dist-info/top_level.txt
