Metadata-Version: 2.0
Name: tensorcomlib
Version: 1.7.0
Summary: For Tensor Decomposition.
Home-page: https://github.com/YiZhiXiaoGuLI/tensorcomlib
Author: Sun Yan
Author-email: sunyanqinyin@aliyun.com
License: MIT
Platform: UNKNOWN
Classifier: License :: OSI Approved :: MIT License
Classifier: Programming Language :: Python
Classifier: Programming Language :: Python :: 3
Classifier: Programming Language :: Python :: 3.6
Classifier: Programming Language :: Python :: Implementation :: CPython
Classifier: Programming Language :: Python :: Implementation :: PyPy
Requires-Python: >=3.6.0
